tvm/__init__.py
tvm/error.py
tvm/generic.py
tvm/libtvm.so
tvm/libtvm_runtime.so
tvm/parser.py
tvm/support.py
tvm/_ffi/__init__.py
tvm/_ffi/_pyversion.py
tvm/_ffi/base.py
tvm/_ffi/libinfo.py
tvm/_ffi/registry.py
tvm/_ffi/runtime_ctypes.py
tvm/_ffi/_ctypes/__init__.py
tvm/_ffi/_ctypes/ndarray.py
tvm/_ffi/_ctypes/object.py
tvm/_ffi/_ctypes/packed_func.py
tvm/_ffi/_ctypes/types.py
tvm/_ffi/_cy2/__init__.py
tvm/_ffi/_cy3/__init__.py
tvm/_ffi/_cy3/core.cpython-310-x86_64-linux-gnu.so
tvm/_ffi/_cython/core.cpp
tvm/arith/__init__.py
tvm/arith/_ffi_api.py
tvm/arith/analyzer.py
tvm/arith/bound.py
tvm/arith/int_set.py
tvm/arith/int_solver.py
tvm/arith/iter_affine_map.py
tvm/arith/pattern.py
tvm/auto_scheduler/__init__.py
tvm/auto_scheduler/_ffi_api.py
tvm/auto_scheduler/compute_dag.py
tvm/auto_scheduler/dispatcher.py
tvm/auto_scheduler/feature.py
tvm/auto_scheduler/loop_state.py
tvm/auto_scheduler/measure.py
tvm/auto_scheduler/measure_record.py
tvm/auto_scheduler/relay_integration.py
tvm/auto_scheduler/search_policy.py
tvm/auto_scheduler/search_task.py
tvm/auto_scheduler/task_scheduler.py
tvm/auto_scheduler/utils.py
tvm/auto_scheduler/workload_registry.py
tvm/auto_scheduler/cost_model/__init__.py
tvm/auto_scheduler/cost_model/cost_model.py
tvm/auto_scheduler/cost_model/xgb_model.py
tvm/auto_scheduler/testing/__init__.py
tvm/auto_scheduler/testing/tune_onnx.py
tvm/auto_scheduler/testing/tune_relay.py
tvm/auto_scheduler/testing/tune_te.py
tvm/autotvm/__init__.py
tvm/autotvm/database.py
tvm/autotvm/env.py
tvm/autotvm/feature.py
tvm/autotvm/record.py
tvm/autotvm/tophub.py
tvm/autotvm/utils.py
tvm/autotvm/graph_tuner/__init__.py
tvm/autotvm/graph_tuner/_base.py
tvm/autotvm/graph_tuner/base_graph_tuner.py
tvm/autotvm/graph_tuner/dynamic_programming_stage.py
tvm/autotvm/graph_tuner/dynamic_programming_tuner.py
tvm/autotvm/graph_tuner/pbqp_tuner.py
tvm/autotvm/graph_tuner/utils/__init__.py
tvm/autotvm/graph_tuner/utils/traverse_graph.py
tvm/autotvm/graph_tuner/utils/utils.py
hhb_tvm-3.2.3.dist-info/METADATA
hhb_tvm-3.2.3.dist-info/WHEEL
hhb_tvm-3.2.3.dist-info/entry_points.txt
hhb_tvm-3.2.3.dist-info/top_level.txt
hhb_tvm-3.2.3.dist-info/RECORD
