Metadata-Version: 2.1
Name: hhb-tvm
Version: 3.2.3
Summary: TVM: An End to End Tensor IR/DSL Stack for Deep Learning Systems
Home-page: https://tvm.apache.org/
Author: Apache TVM
License: Apache
Download-URL: https://github.com/apache/tvm/tags
Keywords: machine learning
Platform: UNKNOWN
Classifier: License :: OSI Approved :: Apache Software License
Classifier: Development Status :: 4 - Beta
Classifier: Intended Audience :: Developers
Classifier: Intended Audience :: Education
Classifier: Intended Audience :: Science/Research
Requires-Dist: attrs
Requires-Dist: cloudpickle
Requires-Dist: decorator
Requires-Dist: ml-dtypes
Requires-Dist: numpy (<2.0.0)
Requires-Dist: psutil
Requires-Dist: scipy
Requires-Dist: tornado
Requires-Dist: typing-extensions
Provides-Extra: all-prod
Requires-Dist: attrs ; extra == 'all-prod'
Requires-Dist: cloudpickle ; extra == 'all-prod'
Requires-Dist: coremltools ; extra == 'all-prod'
Requires-Dist: decorator ; extra == 'all-prod'
Requires-Dist: ethos-u-vela (==3.8.0) ; extra == 'all-prod'
Requires-Dist: future ; extra == 'all-prod'
Requires-Dist: h5py (==2.10.0) ; extra == 'all-prod'
Requires-Dist: ml-dtypes ; extra == 'all-prod'
Requires-Dist: numpy (<2.0.0) ; extra == 'all-prod'
Requires-Dist: onnx ; extra == 'all-prod'
Requires-Dist: onnxoptimizer ; extra == 'all-prod'
Requires-Dist: onnxruntime ; extra == 'all-prod'
Requires-Dist: opencv-python ; extra == 'all-prod'
Requires-Dist: paddlepaddle ; extra == 'all-prod'
Requires-Dist: progressbar ; extra == 'all-prod'
Requires-Dist: protobuf ; extra == 'all-prod'
Requires-Dist: psutil ; extra == 'all-prod'
Requires-Dist: scikit-image ; extra == 'all-prod'
Requires-Dist: scipy ; extra == 'all-prod'
Requires-Dist: six ; extra == 'all-prod'
Requires-Dist: tensorflow ; extra == 'all-prod'
Requires-Dist: tensorflow-estimator ; extra == 'all-prod'
Requires-Dist: tflite ; extra == 'all-prod'
Requires-Dist: torch ; extra == 'all-prod'
Requires-Dist: torchvision ; extra == 'all-prod'
Requires-Dist: tornado ; extra == 'all-prod'
Requires-Dist: typing-extensions ; extra == 'all-prod'
Requires-Dist: xgboost (>=1.1.0) ; extra == 'all-prod'
Provides-Extra: dev
Requires-Dist: astroid ; extra == 'dev'
Requires-Dist: autodocsumm ; extra == 'dev'
Requires-Dist: black (==20.8b1) ; extra == 'dev'
Requires-Dist: commonmark (>=0.7.3) ; extra == 'dev'
Requires-Dist: cpplint ; extra == 'dev'
Requires-Dist: docutils (<0.17) ; extra == 'dev'
Requires-Dist: image ; extra == 'dev'
Requires-Dist: matplotlib ; extra == 'dev'
Requires-Dist: pillow ; extra == 'dev'
Requires-Dist: pylint ; extra == 'dev'
Requires-Dist: sphinx ; extra == 'dev'
Requires-Dist: sphinx-autodoc-annotation ; extra == 'dev'
Requires-Dist: sphinx-gallery ; extra == 'dev'
Requires-Dist: sphinx-rtd-theme ; extra == 'dev'
Requires-Dist: types-psutil ; extra == 'dev'
Provides-Extra: ethosu
Requires-Dist: ethos-u-vela (==3.8.0) ; extra == 'ethosu'
Provides-Extra: importer-caffe
Requires-Dist: numpy (<2.0.0) ; extra == 'importer-caffe'
Requires-Dist: protobuf ; extra == 'importer-caffe'
Requires-Dist: scikit-image ; extra == 'importer-caffe'
Requires-Dist: six ; extra == 'importer-caffe'
Provides-Extra: importer-caffe2
Requires-Dist: future ; extra == 'importer-caffe2'
Requires-Dist: torch ; extra == 'importer-caffe2'
Provides-Extra: importer-coreml
Requires-Dist: coremltools ; extra == 'importer-coreml'
Provides-Extra: importer-darknet
Requires-Dist: opencv-python ; extra == 'importer-darknet'
Provides-Extra: importer-keras
Requires-Dist: tensorflow ; extra == 'importer-keras'
Requires-Dist: tensorflow-estimator ; extra == 'importer-keras'
Provides-Extra: importer-onnx
Requires-Dist: future ; extra == 'importer-onnx'
Requires-Dist: onnx ; extra == 'importer-onnx'
Requires-Dist: onnxoptimizer ; extra == 'importer-onnx'
Requires-Dist: onnxruntime ; extra == 'importer-onnx'
Requires-Dist: torch ; extra == 'importer-onnx'
Requires-Dist: torchvision ; extra == 'importer-onnx'
Provides-Extra: importer-paddle
Requires-Dist: paddlepaddle ; extra == 'importer-paddle'
Provides-Extra: importer-pytorch
Requires-Dist: future ; extra == 'importer-pytorch'
Requires-Dist: torch ; extra == 'importer-pytorch'
Requires-Dist: torchvision ; extra == 'importer-pytorch'
Provides-Extra: importer-tensorflow
Requires-Dist: tensorflow ; extra == 'importer-tensorflow'
Requires-Dist: tensorflow-estimator ; extra == 'importer-tensorflow'
Provides-Extra: importer-tflite
Requires-Dist: tensorflow ; extra == 'importer-tflite'
Requires-Dist: tensorflow-estimator ; extra == 'importer-tflite'
Requires-Dist: tflite ; extra == 'importer-tflite'
Provides-Extra: tvmc
Requires-Dist: ethos-u-vela (==3.8.0) ; extra == 'tvmc'
Requires-Dist: future ; extra == 'tvmc'
Requires-Dist: onnx ; extra == 'tvmc'
Requires-Dist: onnxoptimizer ; extra == 'tvmc'
Requires-Dist: onnxruntime ; extra == 'tvmc'
Requires-Dist: paddlepaddle ; extra == 'tvmc'
Requires-Dist: tensorflow ; extra == 'tvmc'
Requires-Dist: tflite ; extra == 'tvmc'
Requires-Dist: torch ; extra == 'tvmc'
Requires-Dist: torchvision ; extra == 'tvmc'
Requires-Dist: xgboost (>=1.1.0) ; extra == 'tvmc'
Provides-Extra: vitis-ai
Requires-Dist: h5py (==2.10.0) ; extra == 'vitis-ai'
Requires-Dist: progressbar ; extra == 'vitis-ai'
Provides-Extra: xgboost
Requires-Dist: future ; extra == 'xgboost'
Requires-Dist: torch ; extra == 'xgboost'
Requires-Dist: xgboost (>=1.1.0) ; extra == 'xgboost'
